{
    "cluster": "cruddur",
    "launchType": "FARGATE",
    "desiredCount": 1,
    "enableECSManagedTags": true,
    "enableExecuteCommand": true,
    "loadBalancers": [
      {
          "targetGroupArn": "arn:aws:elasticloadbalancing:us-east-1:960757103945:targetgroup/cruddur-backend-flask-tg/ba84df65bd0715df",
          "containerName": "backend-flask",
          "containerPort": 4567
      }
    ],
    "networkConfiguration": {
      "awsvpcConfiguration": {
        "assignPublicIp": "ENABLED",
        "securityGroups": [
          "sg-096393bb23e541ba8"
        ],
        "subnets": [
            "subnet-6ced0d6d",
            "subnet-05ec1249",
            "subnet-d4456e8b",
            "subnet-3fd0e51e",
            "subnet-002a0466",
            "subnet-61423050"
        ]
      }
    },
    "propagateTags": "SERVICE",
    "serviceName": "backend-flask",
    "taskDefinition": "backend-flask",
    "serviceConnectConfiguration": {
      "enabled": true,
      "namespace": "cruddur",
      "services": [
        {
          "portName": "backend-flask",
          "discoveryName": "backend-flask",
          "clientAliases": [{"port": 4567}]
        }
      ]
    }
    
  }